[{
      "id":"1710356546",
      "type":"Квартира",
      "page":"",
      "rent":"",
      "rooms":"2",
      "surface":"55",
      "surface_land":"",
      "price":"$37000",
      "price_sqmt":"",
      "floor":"3",
      "floors":"3",
      "parking":"Прибудинкова територія",
      "region":"",
      "location":"м. Збараж",
      "address":"вул. Михайла Грушевського, 70А",
      "object":"",
      "coordinates":"49.675046,25.759020",
      "date":"2024-03-13",
      "seller":"Наталія Осіпук",
      "phone":"380978979313","description":"Вторинне відремонтоване житло, придатне для проживання",
      "link":"/district/town/zbarazh/apartment/selling-1710356546.html","images":[{"src":"1_livingroom.jpg","alt":"Квартира в м. Збараж","title":"Квартира по вул. Михайла Грушевського, 70А в м. Збараж"},{"src":"2_kidsroom.jpg","alt":"Квартира в м. Збараж","title":"Квартира по вул. Михайла Грушевського, 70А в м. Збараж"},{"src":"3_kitchen.jpg","alt":"Квартира в м. Збараж","title":"Квартира по вул. Михайла Грушевського, 70А в м. Збараж"},{"src":"4_restroom.jpg","alt":"Квартира в м. Збараж","title":"Квартира по вул. Михайла Грушевського, 70А в м. Збараж"}]},{
      "id":"1706993664",
      "type":"Квартира",
      "page":"",
      "rent":"",
      "rooms":"6",
      "surface":"79",
      "surface_land":"",
      "price":"$45000",
      "price_sqmt":"",
      "floor":"1",
      "floors":"2",
      "parking":"Прибудинкова територія, гараж",
      "region":"",
      "location":"м. Збараж",
      "address":"вул. Вишнівецького, 9/8",
      "object":"",
      "coordinates":"49.686903,25.756721",
      "date":"2024-02-03",
      "seller":"Мар'яна Ключка",
      "phone":"380977983564","description":"Вторинне відремонтоване житло, придатне для проживання",
      "link":"/district/town/zbarazh/apartment/selling-1706993664.html","images":[{"src":"1_apartment.jpg","alt":"Квартира в м. Збараж","title":"Квартира по вул. Вишнівецького, 9/8 в м. Збараж"},{"src":"2_livingroom.jpg","alt":"Квартира в м. Збараж","title":"Квартира по вул. Вишнівецького, 9/8 в м. Збараж"},{"src":"3_kitchen.jpg","alt":"Квартира в м. Збараж","title":"Квартира по вул. Вишнівецького, 9/8 в м. Збараж"},{"src":"4_restroom.jpg","alt":"Квартира в м. Збараж","title":"Квартира по вул. Вишнівецького, 9/8 в м. Збараж"}]},{
      "id":"1701349624",
      "type":"Будинок",
      "page":"",
      "rent":"",
      "rooms":"7",
      "surface":"340",
      "surface_land":"1250",
      "price":"$70000",
      "price_sqmt":"",
      "floor":"",
      "floors":"2",
      "parking":"Прибудинкова територія, гараж",
      "region":"",
      "location":"м. Збараж",
      "address":"вул. Івана Крип'якевича, 1",
      "object":"",
      "coordinates":"49.682514,25.756166",
      "date":"2023-11-30",
      "seller":"Ігор Смакула",
      "phone":"380671222595","description":"Вторинне відремонтоване житло з меблями, придатне для проживання",
      "link":"/district/town/zbarazh/house/selling-1701349624.html","images":[{"src":"1_house.jpg","alt":"Будинок в м. Збараж","title":"Будинок по вул. Івана Крип'якевича, 1 в м. Збараж"},{"src":"2_bedroom.jpg","alt":"Будинок в м. Збараж","title":"Будинок по вул. Івана Крип'якевича, 1 в м. Збараж"},{"src":"3_kitchen.jpg","alt":"Будинок в м. Збараж","title":"Будинок по вул. Івана Крип'якевича, 1 в м. Збараж"},{"src":"4_restroom.jpg","alt":"Будинок в м. Збараж","title":"Будинок по вул. Івана Крип'якевича, 1 в м. Збараж"}]},{
      "id":"1700844661",
      "type":"Будинок",
      "page":"",
      "rent":"",
      "rooms":"4",
      "surface":"77",
      "surface_land":"600",
      "price":"$25000",
      "price_sqmt":"",
      "floor":"",
      "floors":"1",
      "parking":"Прибудинкова територія, гараж",
      "region":"",
      "location":"м. Збараж",
      "address":"вул. Івана Котляревського, 22, с. Базаринці, Збаразька територіальна громада",
      "object":"",
      "coordinates":"49.672864,25.781566",
      "date":"2023-11-24",
      "seller":"Богдан Данилюк",
      "phone":"380977767707","description":"Вторинне житло з меблями, придатне для проживання",
      "link":"","images":""},{
      "id":"1700841409",
      "type":"Будинок",
      "page":"",
      "rent":"",
      "rooms":"4",
      "surface":"88",
      "surface_land":"1500",
      "price":"$19000",
      "price_sqmt":"",
      "floor":"",
      "floors":"1",
      "parking":"Прибудинкова територія, гараж",
      "region":"",
      "location":"м. Збараж",
      "address":"вул. Довга, 68",
      "object":"",
      "coordinates":"49.659847,25.768657",
      "date":"2023-11-24",
      "seller":"Наталія Борівець",
      "phone":"380965607976","description":"Вторинне житло, придатне для проживання",
      "link":"","images":""},{
      "id":"1698422979",
      "type":"Квартира",
      "page":"",
      "rent":"",
      "rooms":"3",
      "surface":"56",
      "surface_land":"",
      "price":"$48000",
      "price_sqmt":"",
      "floor":"3",
      "floors":"3",
      "parking":"Прибудинкова територія",
      "region":"",
      "location":"м. Збараж",
      "address":"вул. Михайла Грушевського, 131",
      "object":"",
      "coordinates":"49.674472,25.757574",
      "date":"2023-10-27",
      "seller":"Віктор Люцинак",
      "phone":"380673500871","description":"Вторинне відремонтоване житло з меблями, придатне для проживання",
      "link":"","images":""},{
      "id":"1698422987",
      "type":"Квартира",
      "page":"",
      "rent":"",
      "rooms":"2",
      "surface":"53",
      "surface_land":"",
      "price":"$30000",
      "price_sqmt":"",
      "floor":"5",
      "floors":"5",
      "parking":"Прибудинкова територія",
      "region":"",
      "location":"м. Збараж",
      "address":"вул. Михайла Коцюбинського, 1",
      "object":"",
      "coordinates":"49.675539,25.760805",
      "date":"2023-10-27",
      "seller":"Андрій Бойко",
      "phone":"380967293816","description":"Вторинне відремонтоване житло з меблями, придатне для проживання",
      "link":"","images":""},{
      "id":"1698422975",
      "type":"Квартира",
      "page":"",
      "rent":"",
      "rooms":"1",
      "surface":"37",
      "surface_land":"",
      "price":"$20000",
      "price_sqmt":"",
      "floor":"4",
      "floors":"5",
      "parking":"Прибудинкова територія",
      "region":"",
      "location":"м. Збараж",
      "address":"вул. Михайла Грушевського, 133",
      "object":"",
      "coordinates":"49.674948,25.756884",
      "date":"2023-10-27",
      "seller":"Юлія Шевела",
      "phone":"380971339153","description":"Вторинне відремонтоване житло з меблями, придатне для проживання",
      "link":"","images":""}]
